setup.py
promptlib/__init__.py
promptlib.egg-info/PKG-INFO
promptlib.egg-info/SOURCES.txt
promptlib.egg-info/dependency_links.txt
promptlib.egg-info/top_level.txt