Metadata-Version: 1.0
Name: promptlib
Version: 1.0.0
Summary: Prompt library
Home-page: UNKNOWN
Author: UNKNOWN
Author-email: UNKNOWN
License: UNKNOWN
Platform: UNKNOWN
